{
  "256_centered": {
    "at_0.5": {
      "thr": 0.5,
      "acc": 0.9573,
      "recall": 0.9688,
      "prec": 0.9495,
      "fa": 0.055,
      "FN": 37,
      "FP": 61,
      "f2": 0.9648
    },
    "f2_optimal": {
      "thr": 0.34,
      "acc": 0.9534,
      "recall": 0.9823,
      "prec": 0.9311,
      "fa": 0.0775,
      "FN": 21,
      "FP": 86,
      "f2": 0.9716
    }
  },
  "256_offset": {
    "at_0.5": {
      "thr": 0.5,
      "acc": 0.9115,
      "recall": 0.9333,
      "prec": 0.8991,
      "fa": 0.1117,
      "FN": 79,
      "FP": 124,
      "f2": 0.9262
    },
    "f2_optimal": {
      "thr": 0.49,
      "acc": 0.9067,
      "recall": 0.9375,
      "prec": 0.888,
      "fa": 0.1261,
      "FN": 74,
      "FP": 140,
      "f2": 0.9272
    }
  },
  "512_centered": {
    "at_0.5": {
      "thr": 0.5,
      "acc": 0.9943,
      "recall": 0.9949,
      "prec": 0.9941,
      "fa": 0.0063,
      "FN": 6,
      "FP": 7,
      "f2": 0.9948
    },
    "f2_optimal": {
      "thr": 0.6,
      "acc": 0.9956,
      "recall": 0.9949,
      "prec": 0.9966,
      "fa": 0.0036,
      "FN": 6,
      "FP": 4,
      "f2": 0.9953
    }
  },
  "512_offset": {
    "at_0.5": {
      "thr": 0.5,
      "acc": 0.9786,
      "recall": 0.9848,
      "prec": 0.9741,
      "fa": 0.0279,
      "FN": 18,
      "FP": 31,
      "f2": 0.9826
    },
    "f2_optimal": {
      "thr": 0.48,
      "acc": 0.9778,
      "recall": 0.9856,
      "prec": 0.9717,
      "fa": 0.0306,
      "FN": 17,
      "FP": 34,
      "f2": 0.9828
    }
  }
}